moai/__init__.py
moai/__main__.py
moai/action/__init__.py
moai/action/archive.py
moai/action/diff.py
moai/action/evaluate.py
moai/action/export.py
moai/action/fit.py
moai/action/play.py
moai/action/plot.py
moai/action/reprod.py
moai/action/resume.py
moai/action/train.py
moai/checkpoint/__init__.py
moai/checkpoint/lightning/__init__.py
moai/checkpoint/lightning/noop.py
moai/conf/__init__.py
moai/conf/__pycache__/__init__.cpython-37.pyc
moai/conf/data/cifar10.yaml
moai/conf/data/cifar100.yaml
moai/conf/data/defaults/cifar10.yaml
moai/conf/data/defaults/cifar100.yaml
moai/conf/data/test/augmentation/none.yaml
moai/conf/data/test/augmentation/albumentations/compose.yaml
moai/conf/data/test/augmentation/albumentations/custom.yaml
moai/conf/data/test/augmentation/albumentations/oneof.yaml
moai/conf/data/test/augmentation/albumentations/augmentations/brightness_contrast.yaml
moai/conf/data/test/augmentation/albumentations/augmentations/center_crop.yaml
moai/conf/data/test/augmentation/albumentations/augmentations/channel_dropout.yaml
moai/conf/data/test/augmentation/albumentations/augmentations/channel_shuffle.yaml
moai/conf/data/test/augmentation/albumentations/augmentations/clahe.yaml
moai/conf/data/test/augmentation/albumentations/augmentations/coarse_dropout.yaml
moai/conf/data/test/augmentation/albumentations/augmentations/cutout.yaml
moai/conf/data/test/augmentation/albumentations/augmentations/horizontal_flip.yaml
moai/conf/data/test/augmentation/albumentations/augmentations/noop.yaml
moai/conf/data/test/augmentation/albumentations/augmentations/normalize.yaml
moai/conf/data/test/augmentation/albumentations/augmentations/posterize.yaml
moai/conf/data/test/augmentation/albumentations/augmentations/random_gamma.yaml
moai/conf/data/test/augmentation/albumentations/augmentations/random_sized_crop.yaml
moai/conf/data/test/augmentation/albumentations/augmentations/resize.yaml
moai/conf/data/test/augmentation/albumentations/augmentations/rotate_90.yaml
moai_mdk-0.1.5a34.dist-info/LICENSE
moai_mdk-0.1.5a34.dist-info/METADATA
moai_mdk-0.1.5a34.dist-info/WHEEL
moai_mdk-0.1.5a34.dist-info/entry_points.txt
moai_mdk-0.1.5a34.dist-info/top_level.txt
moai_mdk-0.1.5a34.dist-info/RECORD
