Metadata-Version: 2.1
Name: moai-mdk
Version: 0.1.5a34
Summary: moai: Accelerated, Flexible, Modular, Reproducible, Insightful AI
Home-page: https://github.com/ai-in-motion/moai
Author: AI-in-Motion Team
Author-email: moai@ai-in-motion.dev
License: UNKNOWN
Project-URL: Documentation, https://moai.readthedocs.io/en/latest/
Project-URL: Source, https://github.com/ai-in-motion/moai
Keywords: AI,workflow,framework,PyTorch
Platform: UNKNOWN
Classifier: Development Status :: 3 - Alpha
Classifier: Intended Audience :: Developers
Classifier: Intended Audience :: Science/Research
Classifier: Programming Language :: Python :: 3.7
Classifier: License :: OSI Approved :: Apache Software License
Classifier: Operating System :: OS Independent
Classifier: Topic :: Scientific/Engineering :: Artificial Intelligence
Classifier: Topic :: Software Development :: Libraries
Classifier: Topic :: Software Development :: Libraries :: Python Modules
Requires-Python: ~=3.7
Requires-Dist: omegaconf (==2.0.2)
Requires-Dist: hydra-core (==1.0.3)
Requires-Dist: hydra-colorlog (==1.0.0)
Requires-Dist: pytorch-lightning (==1.5.1)
Requires-Dist: kornia (==0.6.3)
Requires-Dist: visdom
Requires-Dist: hiplot (==0.1.20)
Requires-Dist: opencv-python
Requires-Dist: albumentations (==1.1.0)
Requires-Dist: matplotlib (==3.3.4)
Requires-Dist: toolz
Requires-Dist: tablib
Requires-Dist: json2html
Requires-Dist: pysm (==0.3.9)
Requires-Dist: colour
Requires-Dist: parsedatetime (==2.6)
Requires-Dist: deepdiff (==4.0.9)
Requires-Dist: rich
Requires-Dist: pandas
Requires-Dist: roma
Requires-Dist: trimesh
